officemcp/OfficeMCP.py
officemcp/Officer.py
officemcp/OfficerClient.py
officemcp/__init__.py
officemcp-1.0.5.dist-info/METADATA
officemcp-1.0.5.dist-info/WHEEL
officemcp-1.0.5.dist-info/entry_points.txt
officemcp-1.0.5.dist-info/RECORD
