Metadata-Version: 2.4
Name: officemcp
Version: 1.0.5
Summary: this is an mcp server for you to control office application installed in windows
Author-email: OfficeMCP <youngfe@live.com>
Requires-Python: >=3.12
Requires-Dist: fastmcp>=2.3.3
Requires-Dist: pywin32>=310
